pynemaiqpet/__init__.py
pynemaiqpet/command_line_tools.py
pynemaiqpet/nema_smallanimal.py
pynemaiqpet/nema_wb.py
pynemaiqpet-0.5.4.dist-info/LICENSE
pynemaiqpet-0.5.4.dist-info/METADATA
pynemaiqpet-0.5.4.dist-info/WHEEL
pynemaiqpet-0.5.4.dist-info/entry_points.txt
pynemaiqpet-0.5.4.dist-info/top_level.txt
pynemaiqpet-0.5.4.dist-info/RECORD
