Metadata-Version: 2.1
Name: pynemaiqpet
Version: 0.5.4
Summary: Analysis of PET NEMA IQ phantom scans
Author: Georg Schramm
Maintainer-email: Georg Schramm <georg.schramm@kuleuven.be>
License: MIT License
Project-URL: Repository, https://github.com/gschramm/pynemaiqpet
Classifier: Programming Language :: Python :: 3
Classifier: License :: OSI Approved :: MIT License
Classifier: Operating System :: OS Independent
Requires-Python: >=3.8
License-File: LICENSE
Requires-Dist: pymirc<1,>=0.23
Requires-Dist: nibabel>=3.0
Requires-Dist: matplotlib>=3.1
Requires-Dist: pydicom<3,>=2.0
Requires-Dist: scipy>=1.4
Requires-Dist: pandas>=1.0
Requires-Dist: lmfit>=1.0
